main.py
presets.py
cliops/__init__.py
cliops/cli.py
cliops/presets.py
cliops/core/__init__.py
cliops/core/analyzer.py
cliops/core/cache_manager.py
cliops/core/config.py
cliops/core/config_manager.py
cliops/core/config_validator.py
cliops/core/context_optimizer.py
cliops/core/enhancer.py
cliops/core/errors.py
cliops/core/exceptions.py
cliops/core/intelligence.py
cliops/core/logger.py
cliops/core/memory_manager.py
cliops/core/optimizer.py
cliops/core/patterns.py
cliops/core/performance.py
cliops/core/plugin_manager.py
cliops/core/scanner.py
cliops/core/state.py
cliops/core/ui.py
cliops/core/validator.py
cliops/core/welcome.py
cliops-4.4.4.dist-info/licenses/LICENSE
core/__init__.py
core/analyzer.py
core/config.py
core/context_optimizer.py
core/enhancer.py
core/errors.py
core/intelligence.py
core/optimizer.py
core/patterns.py
core/scanner.py
core/state.py
core/ui.py
core/welcome.py
cliops-4.4.4.dist-info/METADATA
cliops-4.4.4.dist-info/WHEEL
cliops-4.4.4.dist-info/entry_points.txt
cliops-4.4.4.dist-info/top_level.txt
cliops-4.4.4.dist-info/RECORD
